asymmetric_greedy_search/__init__.py
asymmetric_greedy_search/backend_numba.py
asymmetric_greedy_search/backend_numpy.py
asymmetric_greedy_search/core.py
asymmetric_greedy_search-0.1.0.dist-info/licenses/LICENSE
asymmetric_greedy_search-0.1.0.dist-info/METADATA
asymmetric_greedy_search-0.1.0.dist-info/WHEEL
asymmetric_greedy_search-0.1.0.dist-info/top_level.txt
asymmetric_greedy_search-0.1.0.dist-info/RECORD
