Metadata-Version: 2.4
Name: asymmetric-greedy-search
Version: 0.1.0
Summary: A Python implementation of the Asymmetric Greedy Search heuristic solution to the linear sum assignment problem.
Author-email: Keith A Boroevich <keith.boroevich@riken.jp>
License:                     GNU GENERAL PUBLIC LICENSE
Project-URL: Homepage, https://github.com/kaboroevich/asymmetric-greedy-search
Project-URL: Documentation, https://github.com/kaboroevich/asymmetric-greedy-search#readme
Project-URL: Issues, https://github.com/kaboroevich/asymmetric-greedy-search/issues
Keywords: optimization,assignment-problem,linear-sum,heuristics,numba
Classifier: Programming Language :: Python :: 3
Classifier: License :: OSI Approved :: MIT License
Classifier: Operating System :: OS Independent
Classifier: Intended Audience :: Science/Research
Classifier: Topic :: Scientific/Engineering :: Mathematics
Requires-Python: >=3.8
License-File: LICENSE
Requires-Dist: numpy>=1.21
Provides-Extra: numba
Requires-Dist: numba; extra == "numba"
Dynamic: license-file
